codearkt/client.py
codearkt/codeact.py
codearkt/event_bus.py
codearkt/gradio.py
codearkt/llm.py
codearkt/metrics.py
codearkt/otel.py
codearkt/prompt_storage.py
codearkt/py.typed
codearkt/python_executor.py
codearkt/server.py
codearkt/settings.py
codearkt/terminal.py
codearkt/tools.py
codearkt/util.py
codearkt/prompts/default.yaml
codearkt-1.9.5.dist-info/licenses/LICENSE
codearkt-1.9.5.dist-info/METADATA
codearkt-1.9.5.dist-info/WHEEL
codearkt-1.9.5.dist-info/top_level.txt
codearkt-1.9.5.dist-info/RECORD
