Metadata-Version: 2.4
Name: codearkt
Version: 1.9.5
Summary: CodeAct implementation with Docker and MCP
Author-email: Ilya Gusev <phoenixilya@gmail.com>
License:                                  Apache License
Project-URL: Homepage, https://github.com/IlyaGusev/codearkt
Classifier: Programming Language :: Python :: 3
Classifier: License :: OSI Approved :: Apache Software License
Classifier: Operating System :: OS Independent
Requires-Python: >=3.12
License-File: LICENSE
Requires-Dist: academia-mcp>=1.11.1
Requires-Dist: arize-phoenix-otel>=0.12.1
Requires-Dist: docker>=7.1.0
Requires-Dist: fastmcp==2.11.3
Requires-Dist: httpx>=0.27.0
Requires-Dist: jinja2>=3.1.6
Requires-Dist: openai>=1.93.0
Requires-Dist: openinference-instrumentation-openai>=0.1.30
Requires-Dist: pytest-asyncio>=1.0.0
Requires-Dist: types-docker>=7.1.0.20250523
Requires-Dist: types-pyyaml>=6.0.12.20250516
Requires-Dist: wsproto>=1.2.0
Requires-Dist: uvicorn>=0.34.3
Requires-Dist: sse-starlette<3.0.0
Requires-Dist: mcp>=1.10.1
Requires-Dist: gradio==5.29.0
Requires-Dist: tiktoken>=0.11.0
Requires-Dist: prompt-toolkit>=3.0.52
Dynamic: license-file
